pyzillow/__init__.py
pyzillow/pyzillow.py
pyzillow/pyzillowerrors.py
pyzillow-0.7.0.dist-info/AUTHORS.rst
pyzillow-0.7.0.dist-info/LICENSE
pyzillow-0.7.0.dist-info/METADATA
pyzillow-0.7.0.dist-info/WHEEL
pyzillow-0.7.0.dist-info/top_level.txt
pyzillow-0.7.0.dist-info/RECORD
