Metadata-Version: 1.1
Name: pyzillow
Version: 0.7.0
Summary: Python API wrapper for Zillow's API
Home-page: https://github.com/hanneshapke/pyzillow
Author: Hannes Hapke
Author-email: hannes.hapke@gmail.com
License: MIT
Keywords: pyzillow,zillow,api,real estate
Platform: UNKNOWN
Classifier: Development Status :: 4 - Beta
Classifier: Intended Audience :: Developers
Classifier: License :: OSI Approved :: MIT License
Classifier: Natural Language :: English
Classifier: Programming Language :: Python :: 3.6
Classifier: Programming Language :: Python :: 3.7
Classifier: Programming Language :: Python :: 3.8
